setup.cfg
setup.py
graphql/__init__.py
graphql/core/__init__.py
graphql/core/error.py
graphql/core/execution/__init__.py
graphql/core/execution/base.py
graphql/core/execution/executor.py
graphql/core/execution/values.py
graphql/core/execution/middlewares/__init__.py
graphql/core/execution/middlewares/asyncio.py
graphql/core/execution/middlewares/gevent.py
graphql/core/execution/middlewares/sync.py
graphql/core/execution/middlewares/utils.py
graphql/core/language/__init__.py
graphql/core/language/ast.py
graphql/core/language/error.py
graphql/core/language/lexer.py
graphql/core/language/location.py
graphql/core/language/parser.py
graphql/core/language/printer.py
graphql/core/language/source.py
graphql/core/language/visitor.py
graphql/core/language/visitor_meta.py
graphql/core/pyutils/__init__.py
graphql/core/pyutils/default_ordered_dict.py
graphql/core/pyutils/defer.py
graphql/core/pyutils/pair_set.py
graphql/core/type/__init__.py
graphql/core/type/definition.py
graphql/core/type/directives.py
graphql/core/type/introspection.py
graphql/core/type/scalars.py
graphql/core/type/schema.py
graphql/core/utils/__init__.py
graphql/core/utils/ast_from_value.py
graphql/core/utils/ast_to_code.py
graphql/core/utils/ast_to_dict.py
graphql/core/utils/build_ast_schema.py
graphql/core/utils/build_client_schema.py
graphql/core/utils/concat_ast.py
graphql/core/utils/extend_schema.py
graphql/core/utils/get_field_def.py
graphql/core/utils/get_operation_ast.py
graphql/core/utils/introspection_query.py
graphql/core/utils/is_valid_literal_value.py
graphql/core/utils/is_valid_value.py
graphql/core/utils/schema_printer.py
graphql/core/utils/type_comparators.py
graphql/core/utils/type_from_ast.py
graphql/core/utils/type_info.py
graphql/core/utils/value_from_ast.py
graphql/core/validation/__init__.py
graphql/core/validation/context.py
graphql/core/validation/rules/__init__.py
graphql/core/validation/rules/arguments_of_correct_type.py
graphql/core/validation/rules/base.py
graphql_core_tw.egg-info/PKG-INFO
graphql_core_tw.egg-info/SOURCES.txt
graphql_core_tw.egg-info/dependency_links.txt
graphql_core_tw.egg-info/requires.txt
graphql_core_tw.egg-info/top_level.txt
