Metadata-Version: 1.1
Name: graphql-core-tw
Version: 0.4.18
Summary: GraphQL implementation for Python
Home-page: https://github.com/graphql-python/graphql-core
Author: Syrus Akbary, Jake Heinz, Taeho Kim
Author-email: Syrus Akbary <me@syrusakbary.com>, Jake Heinz <me@jh.gg>, Taeho Kim <dittos@gmail.com>
License: MIT
Download-URL: https://github.com/graphql-python/graphql-core/releases
Keywords: api graphql protocol rest
Platform: UNKNOWN
Classifier: Development Status :: 5 - Production/Stable
Classifier: Intended Audience :: Developers
Classifier: Topic :: Software Development :: Libraries
Classifier: Programming Language :: Python :: 2
Classifier: Programming Language :: Python :: 2.7
Classifier: Programming Language :: Python :: 3
Classifier: Programming Language :: Python :: 3.3
Classifier: Programming Language :: Python :: 3.4
Classifier: Programming Language :: Python :: 3.5
Classifier: Programming Language :: Python :: Implementation :: PyPy
Classifier: License :: OSI Approved :: MIT License
Classifier: Topic :: Database :: Front-Ends
Classifier: Topic :: Internet :: WWW/HTTP
